{
	"architecture": [
		{
			"url": "https://api.reelly.io/vault/ZZLvFZFt/J47UZM3KowLIiHy8Fx6XOEaphSA/dY9Bqw../UMO_02_Aerial_EF2_v3+copy.jpg"
		},
		{
			"url": "https://api.reelly.io/vault/ZZLvFZFt/qRJToYSjmHyUQlIYW1Nk_ig0bjw/E90_eQ../UMO_05_Hotel_Entrance_EF2_v2.jpg"
		},
		{
			"url": "https://api.reelly.io/vault/ZZLvFZFt/nyur6a8jtaC1QsEposCxfbcRx3s/5GFfZg../UMO_09_Hotel_Balcony_EF2.jpg"
		},
		{
			"url": "https://api.reelly.io/vault/ZZLvFZFt/4hoYWMj9qE1Hbq-dypOwY24Odog/Li7B8Q../UMO_15_Pods_EF2+copy.jpg"
		},
		{
			"url": "https://api.reelly.io/vault/ZZLvFZFt/irzqGyXwn1nNlfTE9jvmwulZZis/ieN5Ow../OTT_01_FrontView_EF+copy.jpg"
		},
		{
			"url": "https://api.reelly.io/vault/ZZLvFZFt/MYiw3IkhCwP3Iyqz5hMF2uyhVgk/zjnztQ../OTT_02_RearView_EF+copy.jpg"
		},
		{
			"url": "https://api.reelly.io/vault/ZZLvFZFt/MsGJ9oFOWlydUwbu8E4SJQgV2hM/htnbVQ../35.jpg"
		},
		{
			"url": "https://api.reelly.io/vault/ZZLvFZFt/xtGNvs7P4qOCTZxKrhr9KBhpH24/PjRk2A../36.jpg"
		}
	],
	"area": "Yiti, Oman",
	"area_unit": "sqft",
	"brochure_url": "https://drive.google.com/file/d/1jLJS3yZbwSoHtOactnFEs9w_JB1qTp4c/view?usp=sharing",
	"buildings": [
		[
			{
				"Building_ID": "recWlGYrmoftTz0tk",
				"Building_image": [
					{
						"access": "public",
						"meta": {
							"height": 834,
							"width": 1500
						},
						"mime": "image/jpeg",
						"name": "UMO_02_Aerial_EF2_v3 copy.jpg",
						"path": "/vault/ZZLvFZFt/SGrNWg5_aLj5mBLhF7es1mXK8Sw/STW4SQ../UMO_02_Aerial_EF2_v3+copy.jpg",
						"size": 308551,
						"type": "image",
						"url": "https://api.reelly.io/vault/ZZLvFZFt/SGrNWg5_aLj5mBLhF7es1mXK8Sw/STW4SQ../UMO_02_Aerial_EF2_v3+copy.jpg"
					}
				],
				"Completion_date": null,
				"Description": "Studio & 1 bedroom hotel apartments",
				"Name": "Building",
				"Project": [0],
				"created_at": 1719991047000,
				"id": 1626
			}
		],
		[
			{
				"Building_ID": "recr19hDSZbSBVdHV",
				"Building_image": [
					{
						"access": "public",
						"meta": {
							"height": 834,
							"width": 1500
						},
						"mime": "image/jpeg",
						"name": "OTT_01_FrontView_EF copy.jpg",
						"path": "/vault/ZZLvFZFt/NHRpu9D0QkXGrj8NMl-KtpZHx1Q/D_-5dA../OTT_01_FrontView_EF+copy.jpg",
						"size": 308551,
						"type": "image",
						"url": "https://api.reelly.io/vault/ZZLvFZFt/NHRpu9D0QkXGrj8NMl-KtpZHx1Q/D_-5dA../OTT_01_FrontView_EF+copy.jpg"
					}
				],
				"Completion_date": null,
				"Description": "3 bedroom apartments",
				"Name": "Villas",
				"Project": [0],
				"created_at": 1719991048000,
				"id": 1627
			}
		]
	],
	"city": null,
	"completion_datetime": "2028-12-31T00:00:00",
	"coordinates": "23.531502534549645, 58.68644514228943",
	"country": null,
	"cover_image_url": "{\"access\": \"public\", \"path\": \"/vault/ZZLvFZFt/6Gey7B6ozUjk7wXOojUpPaEhFUc/JZb8Zg../cover.jpg\", \"name\": \"cover.jpg\", \"type\": \"image\", \"size\": 98639, \"mime\": \"image/jpeg\", \"meta\": {\"width\": 1500, \"height\": 504}, \"url\": \"https://api.reelly.io/vault/ZZLvFZFt/6Gey7B6ozUjk7wXOojUpPaEhFUc/JZb8Zg../cover.jpg\"}",
	"deposit_description": null,
	"developer": "Dar Global",
	"developer_data": {
		"description": "DarGlobal profoundly believes in the timeless value of luxury, a kind of wealth in constant growth for its own intrinsic nature, that represents one of the wisest and most foresighted investments of our changing times. Established in 2021 to upend the global luxury real estate market, DarGlobal combines experience and innovation to deliver the highest quality properties. World-class architects curate DarGlobal's homes, which are modeled by renowned design and fashion icons; each home is built with the highest quality materials and maintained by top experts within the field. DarGlobal is always the first to scout the most prestigious and attractive locations, providing lucrative investment opportunities for a distinct clientele. Curating and maintaining state-of-the-art experiences requires a high level of engagement, which is ingrained in DarGlobal's DNA when developing projects. In each instance of setting up a new project at a new location, DarGlobal meticulously ensures each detail is fully attended to, ensuring that all desires of their exquisite clientele are fully met.",
		"email": "agents@darglobal.co.uk",
		"id": 379,
		"logo_image": [
			{
				"url": "https://api.reelly.io/vault/ZZLvFZFt/j_MHocngVoO_MVmQPFAaA80EjIM/9vaY9Q../DG_Logo+%28convert.io%29.png"
			}
		],
		"name": "Dar Global",
		"office_address": "35th Floor, Media One Tower, Al Sufouh 2, Dubai,  UAE",
		"website": "https://darglobal.co.uk/",
		"working_hours": [
			{
				"days": "Monday - Friday",
				"time_range": "9 AM - 6 PM"
			},
			{
				"days": "Saturday - Sunday",
				"time_range": "Day off"
			}
		]
	},
	"developer_website": "https://darglobal.co.uk/",
	"facilities": [
		{
			"image": {
				"url": "https://api.reelly.io/vault/ZZLvFZFt/4LWL3MRcFfCm4xDcNR8vW9BMH0o/poBFQA../OTG_01_Facade_EF_v2+copy.jpg"
			},
			"image_source": "Visualisation from developer",
			"name": " Trump International Golf Club"
		},
		{
			"image": {
				"url": "https://api.reelly.io/vault/ZZLvFZFt/Xf0HqOrUcOcCbwFWeCg7RsaMhqk/Pc62bg../66.jpg"
			},
			"image_source": "Visualisation from developer",
			"name": " Trump Members Only Club "
		},
		{
			"image": {
				"url": "https://api.reelly.io/vault/ZZLvFZFt/c7DM4T7qrqhXBgUBYv7RTldm_lI/mj7uBA../UMO_14_SkyBar_EF2+copy.jpg"
			},
			"image_source": "Visualisation from developer",
			"name": "Cliff Night Club"
		},
		{
			"image": {
				"url": "https://api.reelly.io/vault/ZZLvFZFt/ML0sLilqCgCLe91ls920FE7c3ok/6JYIcg../70.jpg"
			},
			"image_source": "Visualisation from developer",
			"name": "Trump Hotels Hanging Suites"
		},
		{
			"image": {
				"url": "https://api.reelly.io/vault/ZZLvFZFt/FtDTKxJ1dg4ALkgOrcnu6vi1JZA/o9DdDg../42.jpg"
			},
			"image_source": "Visualisation from developer",
			"name": " Plazas, Cafes & Restaurants"
		},
		{
			"image": {
				"url": "https://api.reelly.io/vault/ZZLvFZFt/qZzrXa1hwglXaRkFLGDIbzpJ0cY/Kg3C6w../OGI_02_Gym_EF+copy.jpg"
			},
			"image_source": "Visualisation from developer",
			"name": "Fitness Center"
		},
		{
			"image": {
				"url": "https://api.reelly.io/vault/ZZLvFZFt/tYTEndhHzhi2Utwqxb6nfaC3rpU/MgKk0g../34.jpg"
			},
			"image_source": "Visualisation from developer",
			"name": "Promenades Area"
		},
		{
			"image": {
				"url": "https://api.reelly.io/vault/ZZLvFZFt/JQQn8KykQsGvhqVS_ZQEhuVHYu0/y_dboA../walking-person-girl-trail-sport-meadow-233546-pxhere.com.jpg"
			},
			"image_source": "Image for general understanding",
			"name": " Hiking & Running Trail"
		},
		{
			"image": {
				"url": "https://api.reelly.io/vault/ZZLvFZFt/b3_1FhZmN1vPd_L3k3ax1obezwU/87_MHQ../Benasque-TrackMTB-1.jpg"
			},
			"image_source": "Image for general understanding",
			"name": " Mountain Bike Trail"
		},
		{
			"image": {
				"url": "https://api.reelly.io/vault/ZZLvFZFt/t1y2fZKAp3NpNrdk9AQQ-uWGi5I/t_XRGg../76.jpg"
			},
			"image_source": "Visualisation from developer",
			"name": "Viewing Deck"
		},
		{
			"image": {
				"url": "https://api.reelly.io/vault/ZZLvFZFt/MekS_jj7O-yHNNkJE1rQ3hIJXEk/Xjp8Ig../85.jpg"
			},
			"image_source": "Visualisation from developer",
			"name": " Swimming Pools"
		},
		{
			"image": {
				"url": "https://api.reelly.io/vault/ZZLvFZFt/Lv-I4ELte7gPUm3PFr0dnkkuZfI/-uhxhA../AdobeStock_211595801.jpg"
			},
			"image_source": "Image for general understanding",
			"name": "Kids Play Area"
		},
		{
			"image": {
				"url": "https://api.reelly.io/vault/ZZLvFZFt/wrIWqdiRxtDesR7v0EKvXQzwOs0/ugQcUQ../218707_5.jpg"
			},
			"image_source": "Image for general understanding",
			"name": " Life-Size Chess Board"
		},
		{
			"image": {
				"url": "https://api.reelly.io/vault/ZZLvFZFt/dL6xnioYplbsZ4XQTxAa1V7Ih58/YUO6Lg../79.jpg"
			},
			"image_source": "Visualisation from developer",
			"name": " Aida Beach"
		},
		{
			"image": {
				"url": "https://api.reelly.io/vault/ZZLvFZFt/F-CxjdDuKxYBsK93LIb-HeUKXGw/i9QQRw../orig+%28convert.io%29.jpg"
			},
			"image_source": "Image for general understanding",
			"name": " Wellness Center"
		}
	],
	"furnishing": "Yes",
	"has_escrow": false,
	"id": 1614,
	"interior": [
		{
			"url": "https://api.reelly.io/vault/ZZLvFZFt/pW0Aqq_Vc_cXgPPBsbkx1GMhrVU/ew3chw../OTH_03_Deluxe_Suite_Living_Room_EF+copy.jpg"
		},
		{
			"url": "https://api.reelly.io/vault/ZZLvFZFt/hULucSGoOranCQkYnINn9Aknv8E/fvM7Yg../OTH_05_Deluxe_Suite_Master_Bedroom_EF+copy.jpg"
		},
		{
			"url": "https://api.reelly.io/vault/ZZLvFZFt/0-DIg6z8SNb6v4iW_NBPz1XNZvg/5x1rBw../OTT_03_Living_EF+copy.jpg"
		},
		{
			"url": "https://api.reelly.io/vault/ZZLvFZFt/TTqODb7aldbdi-dCfh6T7FoR7J4/mpGb3w../OTT_04_Kitchen_Dining_EF+copy.jpg"
		},
		{
			"url": "https://api.reelly.io/vault/ZZLvFZFt/JOTAJ3IfJH_DsMKkH5ijVH-tGtc/kaN6Hw../OTT_05_Bedroom_EF+copy.jpg"
		}
	],
	"is_partner_project": false,
	"layouts_pdf": "https://api.reelly.io/vault/ZZLvFZFt/KzkZobqSbloMM4tqokdhETqEXPY/LZbu0Q../Floor+plans.pdf",
	"lobby": [
		{
			"url": "https://api.reelly.io/vault/ZZLvFZFt/0YSE89tfjYecBdVKqrhalmlpewQ/VKtHow../OTH_01_Main_Lobby_EF+copy.jpg"
		},
		{
			"url": "https://api.reelly.io/vault/ZZLvFZFt/RJXmr-KyNF_T42hIsW3cl5FhZTc/1j7i1g../OGI_01_Lobby_EF+copy.jpg"
		}
	],
	"map_points": [],
	"master_plan": [
		{
			"url": "https://api.reelly.io/vault/ZZLvFZFt/ugw2B15c0OSEyvj8ctkDPNFP5ao/jw_M3Q../master.png"
		}
	],
	"max_area": 1797.6718971962343,
	"max_price": null,
	"min_area": 465.7650186915868,
	"min_price": 1099798.02,
	"min_price_aed": 1099798.02,
	"name": "Trump International Resort",
	"overview": "##### Project general facts\n\nTrump International Resort offers an extraordinary blend of luxury and exclusivity, with meticulously designed and furnished villas and apartments that epitomize the pinnacle of sophistication. Nestled 130 meters above sea level, these project provide direct sea views, creating a serene and majestic living experience. Every detail, down to the last teacup, is curated to perfection, making ownership a once-in-a-lifetime opportunity.\n\nAll villas and apartments are designed in a sophisticated style and fully equipped to European standards: furniture, dishes, essentials, and appliances, including a washing machine, ensuring guests can comfortably reside for both short and long-term stays. In addition to the standart villas, the hotel features unique cliff-hanging suites that boast private pools, capturing breathtaking views of the horizon. These spacious suites are equipped with plush king-sized beds with premium linens, spa-like en-suite bathrooms with modern fixtures, offering an unparalleled standard of comfort and luxury.\n\nSituated by the Championship Golf Course, the exclusive members-only club complements the golfing lifestyle with a full social calendar and world-class amenities tailored to discerning tastes.\n\n##### Finishing and materials\n\nThe apartments and villas are fully finished using high quality modern materials.\n\n##### Kitchen and appliances\n\nEquipped kitchen.\n\n##### Furnishing\n\nYes.\n\n##### Location description and benefits\n\nYiti, Oman, is a picturesque and tranquil coastal area located a short distance from Muscat, the capital city. Known for its stunning natural beauty, Yiti offers a serene escape with its pristine beaches, dramatic rocky cliffs, and clear turquoise waters. This hidden gem is surrounded by rugged mountains, providing a perfect blend of sea and landscape that is ideal for outdoor activities such as hiking, swimming, and picnicking.\n\nThe area is also a developing hub for luxury tourism, with plans for high-end resorts and residential communities aimed at enhancing its appeal to both locals and international visitors. The untouched beauty of Yiti Beach is one of its main attractions, featuring soft sands and a peaceful environment, making it a favored spot for beachgoers seeking a more secluded experience away from the busier tourist spots.\n\nYiti's proximity to Muscat makes it accessible yet sufficiently remote to maintain its tranquil atmosphere. The drive to Yiti offers scenic views of the coastline and mountains, further enriching the visitor experience. This area is increasingly recognized for its potential as a major tourist destination in Oman, promising future development while preserving its natural charm and ecological significance.\n",
	"parking": "",
	"parkings": [
		[
			{
				"Parking_spaces": 1,
				"Unit_bedrooms": ["Studio", "1BR"],
				"Unit_type": "Apartments"
			}
		],
		[
			{
				"Parking_spaces": 2,
				"Unit_bedrooms": ["3BR"],
				"Unit_type": "Villas"
			}
		]
	],
	"payment_plans": [
		{
			"Payments": [
				[
					{
						"Order": 1,
						"Payment_time": "On booking",
						"Percent_of_payment": "20"
					}
				],
				[
					{
						"Order": 2,
						"Payment_time": "During construction",
						"Percent_of_payment": "45"
					}
				],
				[
					{
						"Order": 3,
						"Payment_time": "Upon Handover",
						"Percent_of_payment": "35"
					}
				]
			],
			"Plan_name": "Payment Plan",
			"months_after_handover": 0
		}
	],
	"post_handover": false,
	"price_currency": "AED",
	"readiness": "",
	"sale_status": "On sale",
	"service_charge": "4 AED/sqft",
	"slug": "dar-global-trump-international-resort",
	"status": "Presale",
	"unit_availability": [],
	"unit_blocks": [
		{
			"area_unit": "sqft",
			"id": 4861,
			"normalized_type": "Hotel Apartments",
			"price_currency": "AED",
			"typical_unit_image_url": "[{\"access\":\"public\",\"path\":\"\\/vault\\/ZZLvFZFt\\/W3jtjYY72FCIKahfashJU3KSdFY\\/QqE8Sg..\\/std.png\",\"name\":\"std.png\",\"type\":\"image\",\"size\":308551,\"mime\":\"image\\/png\",\"meta\":{\"width\":800,\"height\":800},\"url\":\"https:\\/\\/xdil-qda0-zofk.m2.xano.io\\/vault\\/ZZLvFZFt\\/W3jtjYY72FCIKahfashJU3KSdFY\\/QqE8Sg..\\/std.png\"}]",
			"unit_bedrooms": "Studio",
			"unit_type": "Hotel Apartments",
			"units_amount": 0,
			"units_area_from": null,
			"units_area_from_m2": "43.271028037383",
			"units_area_to": null,
			"units_area_to_m2": "62.336448598131",
			"units_price_from": 1663616,
			"units_price_from_aed": 1663616,
			"units_price_to": 1991302,
			"units_price_to_aed": 1991302
		},
		{
			"area_unit": "sqft",
			"id": 4862,
			"normalized_type": "Hotel Apartments",
			"price_currency": "AED",
			"typical_unit_image_url": "[{\"access\":\"public\",\"path\":\"\\/vault\\/ZZLvFZFt\\/HfiSgQF1woL1bOxQmuOSDyUYGfk\\/Fuh4Tg..\\/1br.png\",\"name\":\"1br.png\",\"type\":\"image\",\"size\":308551,\"mime\":\"image\\/png\",\"meta\":{\"width\":800,\"height\":800},\"url\":\"https:\\/\\/xdil-qda0-zofk.m2.xano.io\\/vault\\/ZZLvFZFt\\/HfiSgQF1woL1bOxQmuOSDyUYGfk\\/Fuh4Tg..\\/1br.png\"}]",
			"unit_bedrooms": "Junior Suite",
			"unit_type": "Hotel Apartments",
			"units_amount": 0,
			"units_area_from": null,
			"units_area_from_m2": "74.485981308411",
			"units_area_to": null,
			"units_area_to_m2": "138.78504672897",
			"units_price_from": null,
			"units_price_from_aed": null,
			"units_price_to": null,
			"units_price_to_aed": null
		},
		{
			"area_unit": "sqft",
			"id": 4863,
			"normalized_type": "Villa",
			"price_currency": "AED",
			"typical_unit_image_url": "[{\"access\":\"public\",\"path\":\"\\/vault\\/ZZLvFZFt\\/x_-YYfNxhFkxhMlHJWoHWQvVytk\\/QmkzCA..\\/villa.png\",\"name\":\"villa.png\",\"type\":\"image\",\"size\":308551,\"mime\":\"image\\/png\",\"meta\":{\"width\":1000,\"height\":1000},\"url\":\"https:\\/\\/xdil-qda0-zofk.m2.xano.io\\/vault\\/ZZLvFZFt\\/x_-YYfNxhFkxhMlHJWoHWQvVytk\\/QmkzCA..\\/villa.png\"}]",
			"unit_bedrooms": "3 bedroom",
			"unit_type": "Villa",
			"units_amount": 0,
			"units_area_from": null,
			"units_area_from_m2": "128.78504672897",
			"units_area_to": null,
			"units_area_to_m2": "167.00934579439",
			"units_price_from": 4343269,
			"units_price_from_aed": 4343269,
			"units_price_to": 6336222,
			"units_price_to_aed": 6336222
		},
		{
			"area_unit": "sqft",
			"id": 4863,
			"normalized_type": "Villas",
			"price_currency": "AED",
			"typical_unit_image_url": "[{\"access\":\"public\",\"path\":\"\\/vault\\/ZZLvFZFt\\/x_-YYfNxhFkxhMlHJWoHWQvVytk\\/QmkzCA..\\/villa.png\",\"name\":\"villa.png\",\"type\":\"image\",\"size\":308551,\"mime\":\"image\\/png\",\"meta\":{\"width\":1000,\"height\":1000},\"url\":\"https:\\/\\/xdil-qda0-zofk.m2.xano.io\\/vault\\/ZZLvFZFt\\/x_-YYfNxhFkxhMlHJWoHWQvVytk\\/QmkzCA..\\/villa.png\"}]",
			"unit_bedrooms": "3 bedroom",
			"unit_type": null,
			"units_amount": 0,
			"units_area_from": 1386.22936448596,
			"units_area_from_m2": 128.78504672897,
			"units_area_to": 1797.6718971962343,
			"units_area_to_m2": 167.00934579439,
			"units_price_from": 3599338.96,
			"units_price_from_aed": 3599338.96,
			"units_price_to": 0,
			"units_price_to_aed": 0
		},
		{
			"area_unit": "sqft",
			"id": 4867,
			"normalized_type": "Hotel Apartments",
			"price_currency": "AED",
			"typical_unit_image_url": "[{\"access\":\"public\",\"path\":\"\\/vault\\/ZZLvFZFt\\/1L30YyhNbHHgCAMGw9UfJ0zvUs0\\/-I1_og..\\/1%D0%BA.png\",\"name\":\"1\\u043a.png\",\"type\":\"image\",\"size\":308551,\"mime\":\"image\\/png\",\"meta\":{\"width\":800,\"height\":800},\"url\":\"https:\\/\\/xdil-qda0-zofk.m2.xano.io\\/vault\\/ZZLvFZFt\\/1L30YyhNbHHgCAMGw9UfJ0zvUs0\\/-I1_og..\\/1%D0%BA.png\"}]",
			"unit_bedrooms": "Suite",
			"unit_type": "Hotel Apartments",
			"units_amount": 0,
			"units_area_from": null,
			"units_area_from_m2": "95.607476635514",
			"units_area_to": null,
			"units_area_to_m2": "0",
			"units_price_from": 3684205,
			"units_price_from_aed": 3684205,
			"units_price_to": 5368427,
			"units_price_to_aed": 5368427
		}
	],
	"video_url": "https://www.youtube.com/watch?v=rf7xlFP4MK4",
	"website": "https://platform.reelly.io/project?project=recM1k9oeYJpcitQD"
}
